mcp_file_tool/__init__.py
mcp_file_tool/__main__.py
mcp_file_tool/chunkio.py
mcp_file_tool/config.py
mcp_file_tool/indexer.py
mcp_file_tool/locks.py
mcp_file_tool/logging_conf.py
mcp_file_tool/py.typed
mcp_file_tool/search.py
mcp_file_tool/server.py
mcp_file_tool/types.py
mcp_file_tool-0.1.3.dist-info/licenses/LICENSE
mcp_file_tool-0.1.3.dist-info/METADATA
mcp_file_tool-0.1.3.dist-info/WHEEL
mcp_file_tool-0.1.3.dist-info/entry_points.txt
mcp_file_tool-0.1.3.dist-info/top_level.txt
mcp_file_tool-0.1.3.dist-info/RECORD
