Metadata-Version: 2.4
Name: mcp-file-tool
Version: 0.1.3
Summary: MCP tools for large text files: chunked IO, search, and SQLite inverted index
Author-email: Trae AI <opensource@trae.ai>
License: MIT License
Project-URL: Homepage, https://example.com/mcp-file-tool
Project-URL: Source, https://example.com/mcp-file-tool
Classifier: Development Status :: 3 - Alpha
Classifier: Intended Audience :: Developers
Classifier: License :: OSI Approved :: MIT License
Classifier: Programming Language :: Python
Classifier: Programming Language :: Python :: 3
Classifier: Programming Language :: Python :: 3 :: Only
Classifier: Programming Language :: Python :: 3.8
Classifier: Programming Language :: Python :: 3.11
Classifier: Topic :: Software Development :: Libraries
Classifier: Topic :: Text Processing
Requires-Python: >=3.8
License-File: LICENSE
Requires-Dist: mcp>=1.20.0
Dynamic: license-file
